kerasfuse/__init__.py
kerasfuse/activations/__init__.py
kerasfuse/activations/gelu.py
kerasfuse/dataset/__init__.py
kerasfuse/dataset/data_augmentation.py
kerasfuse/dataset/generate_class_weights.py
kerasfuse/dataset/load_images.py
kerasfuse/evaluate.py
kerasfuse/losses/__init__.py
kerasfuse/losses/dice_loss.py
kerasfuse/losses/focal_loss.py
kerasfuse/losses/loss_functions.py
kerasfuse/metrics/__init__.py
kerasfuse/metrics/metrics.py
kerasfuse/models/__init__.py
kerasfuse/models/blocks/MultiHeadSelfAttention.py
kerasfuse/models/blocks/TransformerBlock.py
kerasfuse/models/blocks/VisionTransformer.py
kerasfuse/models/blocks/__init__.py
kerasfuse/models/blocks/autoencoder.py
kerasfuse/models/blocks/mlp.py
kerasfuse/models/densenet.py
kerasfuse/models/layers/__init__.py
kerasfuse/models/layers/convutils.py
kerasfuse/models/layers/readme.md
kerasfuse/models/mobilenet.py
kerasfuse/models/resnet.py
kerasfuse/models/u_net.py
kerasfuse/models/v_net.py
kerasfuse/train.py
kerasfuse/visualizations/grad_cam.py
kerasfuse-0.1.dist-info/LICENSE
kerasfuse-0.1.dist-info/METADATA
kerasfuse-0.1.dist-info/WHEEL
kerasfuse-0.1.dist-info/RECORD
