Metadata-Version: 2.1
Name: kerasfuse
Version: 0.1
Summary: KerasFuse is a Python library that combines the power of TensorFlow and Keras with various computer vision techniques for medical image analysis tasks.
Home-page: https://github.com/ayyucedemirbas/KerasFuse
Keywords: Tensorflow,Keras,KerasFuse
Author: Ayyuce Demirbas
Author-email: a.ayyuced@gmail.com
Maintainer: Ayyuce Demirbas
Maintainer-email: a.ayyuced@gmail.com
Requires-Python: >=3.8.1,<3.12.0
Classifier: Development Status :: 3 - Alpha
Classifier: License :: OSI Approved :: GNU General Public License v3 or later (GPLv3+)
Classifier: Natural Language :: English
Classifier: Operating System :: OS Independent
Classifier: Programming Language :: Python :: 3
Classifier: Programming Language :: Python :: 3.9
Classifier: Programming Language :: Python :: 3.10
Classifier: Programming Language :: Python :: 3.11
Classifier: Programming Language :: Python :: 3.8
Requires-Dist: keras (>=2.12.0,<3.0.0)
Requires-Dist: matplotlib (>=3.7.1,<4.0.0)
Requires-Dist: opencv-python (>=4.7.0.72,<5.0.0.0)
Requires-Dist: scikit-learn (>=1.2.2,<2.0.0)
Requires-Dist: tensorflow (>=2.12.0) ; sys_platform != "darwin"
Requires-Dist: tensorflow-macos (>=2.12.0) ; sys_platform == "darwin"
Project-URL: Documentation, https://github.com/ayyucedemirbas/KerasFuse/blob/main/README.md
Project-URL: Repository, https://github.com/ayyucedemirbas/KerasFuse
